MANIFEST.in
__init__.py
hmatch.py
request.py
setup.cfg
setup.py
request_1InterIIT.egg-info/PKG-INFO
request_1InterIIT.egg-info/SOURCES.txt
request_1InterIIT.egg-info/dependency_links.txt
request_1InterIIT.egg-info/entry_points.txt
request_1InterIIT.egg-info/not-zip-safe
request_1InterIIT.egg-info/requires.txt
request_1InterIIT.egg-info/top_level.txt