Metadata-Version: 2.1
Name: request-1InterIIT
Version: 3
Summary: Request Match
Home-page: https://elis.cc
Author: Elis
Author-email: me@elis.cc
License: APACHE License
Keywords: hmatch,request
Platform: UNKNOWN
